odoo/addons/sale_fixed_discount/README.rst
odoo/addons/sale_fixed_discount/__init__.py
odoo/addons/sale_fixed_discount/__manifest__.py
odoo/addons/sale_fixed_discount/i18n/ca.po
odoo/addons/sale_fixed_discount/i18n/es.po
odoo/addons/sale_fixed_discount/i18n/it.po
odoo/addons/sale_fixed_discount/i18n/pt.po
odoo/addons/sale_fixed_discount/i18n/sale_fixed_discount.pot
odoo/addons/sale_fixed_discount/models/__init__.py
odoo/addons/sale_fixed_discount/models/sale_order.py
odoo/addons/sale_fixed_discount/readme/CONFIGURE.rst
odoo/addons/sale_fixed_discount/readme/CONTRIBUTORS.rst
odoo/addons/sale_fixed_discount/readme/DESCRIPTION.rst
odoo/addons/sale_fixed_discount/readme/INSTALL.rst
odoo/addons/sale_fixed_discount/readme/USAGE.rst
odoo/addons/sale_fixed_discount/reports/report_sale_order.xml
odoo/addons/sale_fixed_discount/static/description/icon.png
odoo/addons/sale_fixed_discount/static/description/index.html
odoo/addons/sale_fixed_discount/tests/__init__.py
odoo/addons/sale_fixed_discount/tests/test_sale_fixed_discount.py
odoo/addons/sale_fixed_discount/views/account_invoice_views.xml
odoo/addons/sale_fixed_discount/views/sale_order_views.xml
odoo12_addon_sale_fixed_discount-12.0.1.0.0.99.dev15.dist-info/METADATA
odoo12_addon_sale_fixed_discount-12.0.1.0.0.99.dev15.dist-info/WHEEL
odoo12_addon_sale_fixed_discount-12.0.1.0.0.99.dev15.dist-info/top_level.txt
odoo12_addon_sale_fixed_discount-12.0.1.0.0.99.dev15.dist-info/RECORD
